[{"contact":"聯絡方式0","risk":"風險與挑展\r\n blablabla 0","return":"退換貨\r\n blablabla 0","createTime":1681626869224,"updateTime":1681626869224},{"contact":"聯絡方式1","risk":"風險與挑展\r\n blablabla 1","return":"退換貨\r\n blablabla 1","createTime":1681626869225,"updateTime":1681626869225},{"contact":"聯絡方式2","risk":"風險與挑展\r\n blablabla 2","return":"退換貨\r\n blablabla 2","createTime":1681626869226,"updateTime":1681626869226},{"contact":"聯絡方式3","risk":"風險與挑展\r\n blablabla 3","return":"退換貨\r\n blablabla 3","createTime":1681626869227,"updateTime":1681626869227},{"contact":"聯絡方式4","risk":"風險與挑展\r\n blablabla 4","return":"退換貨\r\n blablabla 4","createTime":1681626869228,"updateTime":1681626869228},{"contact":"聯絡方式5","risk":"風險與挑展\r\n blablabla 5","return":"退換貨\r\n blablabla 5","createTime":1681626869229,"updateTime":1681626869229},{"contact":"聯絡方式6","risk":"風險與挑展\r\n blablabla 6","return":"退換貨\r\n blablabla 6","createTime":1681626869230,"updateTime":1681626869230},{"contact":"聯絡方式7","risk":"風險與挑展\r\n blablabla 7","return":"退換貨\r\n blablabla 7","createTime":1681626869231,"updateTime":1681626869231},{"contact":"聯絡方式8","risk":"風險與挑展\r\n blablabla 8","return":"退換貨\r\n blablabla 8","createTime":1681626869232,"updateTime":1681626869232},{"contact":"聯絡方式9","risk":"風險與挑展\r\n blablabla 9","return":"退換貨\r\n blablabla 9","createTime":1681626869233,"updateTime":1681626869233},{"contact":"聯絡方式10","risk":"風險與挑展\r\n blablabla 10","return":"退換貨\r\n blablabla 10","createTime":1681626869234,"updateTime":1681626869234},{"contact":"聯絡方式11","risk":"風險與挑展\r\n blablabla 11","return":"退換貨\r\n blablabla 11","createTime":1681626869235,"updateTime":1681626869235},{"contact":"聯絡方式12","risk":"風險與挑展\r\n blablabla 12","return":"退換貨\r\n blablabla 12","createTime":1681626869236,"updateTime":1681626869236},{"contact":"聯絡方式13","risk":"風險與挑展\r\n blablabla 13","return":"退換貨\r\n blablabla 13","createTime":1681626869237,"updateTime":1681626869237},{"contact":"聯絡方式14","risk":"風險與挑展\r\n blablabla 14","return":"退換貨\r\n blablabla 14","createTime":1681626869238,"updateTime":1681626869238},{"contact":"聯絡方式15","risk":"風險與挑展\r\n blablabla 15","return":"退換貨\r\n blablabla 15","createTime":1681626869239,"updateTime":1681626869239},{"contact":"聯絡方式16","risk":"風險與挑展\r\n blablabla 16","return":"退換貨\r\n blablabla 16","createTime":1681626869240,"updateTime":1681626869240},{"contact":"聯絡方式17","risk":"風險與挑展\r\n blablabla 17","return":"退換貨\r\n blablabla 17","createTime":1681626869241,"updateTime":1681626869241},{"contact":"聯絡方式18","risk":"風險與挑展\r\n blablabla 18","return":"退換貨\r\n blablabla 18","createTime":1681626869242,"updateTime":1681626869242},{"contact":"聯絡方式19","risk":"風險與挑展\r\n blablabla 19","return":"退換貨\r\n blablabla 19","createTime":1681626869243,"updateTime":1681626869243},{"contact":"聯絡方式20","risk":"風險與挑展\r\n blablabla 20","return":"退換貨\r\n blablabla 20","createTime":1681626869244,"updateTime":1681626869244},{"contact":"聯絡方式21","risk":"風險與挑展\r\n blablabla 21","return":"退換貨\r\n blablabla 21","createTime":1681626869245,"updateTime":1681626869245},{"contact":"聯絡方式22","risk":"風險與挑展\r\n blablabla 22","return":"退換貨\r\n blablabla 22","createTime":1681626869246,"updateTime":1681626869246},{"contact":"聯絡方式23","risk":"風險與挑展\r\n blablabla 23","return":"退換貨\r\n blablabla 23","createTime":1681626869247,"updateTime":1681626869247},{"contact":"聯絡方式24","risk":"風險與挑展\r\n blablabla 24","return":"退換貨\r\n blablabla 24","createTime":1681626869248,"updateTime":1681626869248},{"contact":"聯絡方式25","risk":"風險與挑展\r\n blablabla 25","return":"退換貨\r\n blablabla 25","createTime":1681626869249,"updateTime":1681626869249},{"contact":"聯絡方式26","risk":"風險與挑展\r\n blablabla 26","return":"退換貨\r\n blablabla 26","createTime":1681626869250,"updateTime":1681626869250},{"contact":"聯絡方式27","risk":"風險與挑展\r\n blablabla 27","return":"退換貨\r\n blablabla 27","createTime":1681626869251,"updateTime":1681626869251},{"contact":"聯絡方式28","risk":"風險與挑展\r\n blablabla 28","return":"退換貨\r\n blablabla 28","createTime":1681626869252,"updateTime":1681626869252},{"contact":"聯絡方式29","risk":"風險與挑展\r\n blablabla 29","return":"退換貨\r\n blablabla 29","createTime":1681626869253,"updateTime":1681626869253},{"contact":"聯絡方式30","risk":"風險與挑展\r\n blablabla 30","return":"退換貨\r\n blablabla 30","createTime":1681626869254,"updateTime":1681626869254},{"contact":"聯絡方式31","risk":"風險與挑展\r\n blablabla 31","return":"退換貨\r\n blablabla 31","createTime":1681626869255,"updateTime":1681626869255},{"contact":"聯絡方式32","risk":"風險與挑展\r\n blablabla 32","return":"退換貨\r\n blablabla 32","createTime":1681626869256,"updateTime":1681626869256},{"contact":"聯絡方式33","risk":"風險與挑展\r\n blablabla 33","return":"退換貨\r\n blablabla 33","createTime":1681626869257,"updateTime":1681626869257},{"contact":"聯絡方式34","risk":"風險與挑展\r\n blablabla 34","return":"退換貨\r\n blablabla 34","createTime":1681626869258,"updateTime":1681626869258},{"contact":"聯絡方式35","risk":"風險與挑展\r\n blablabla 35","return":"退換貨\r\n blablabla 35","createTime":1681626869259,"updateTime":1681626869259},{"contact":"聯絡方式36","risk":"風險與挑展\r\n blablabla 36","return":"退換貨\r\n blablabla 36","createTime":1681626869260,"updateTime":1681626869260},{"contact":"聯絡方式37","risk":"風險與挑展\r\n blablabla 37","return":"退換貨\r\n blablabla 37","createTime":1681626869261,"updateTime":1681626869261},{"contact":"聯絡方式38","risk":"風險與挑展\r\n blablabla 38","return":"退換貨\r\n blablabla 38","createTime":1681626869262,"updateTime":1681626869262},{"contact":"聯絡方式39","risk":"風險與挑展\r\n blablabla 39","return":"退換貨\r\n blablabla 39","createTime":1681626869263,"updateTime":1681626869263},{"contact":"聯絡方式40","risk":"風險與挑展\r\n blablabla 40","return":"退換貨\r\n blablabla 40","createTime":1681626869264,"updateTime":1681626869264},{"contact":"聯絡方式41","risk":"風險與挑展\r\n blablabla 41","return":"退換貨\r\n blablabla 41","createTime":1681626869265,"updateTime":1681626869265},{"contact":"聯絡方式42","risk":"風險與挑展\r\n blablabla 42","return":"退換貨\r\n blablabla 42","createTime":1681626869266,"updateTime":1681626869266},{"contact":"聯絡方式43","risk":"風險與挑展\r\n blablabla 43","return":"退換貨\r\n blablabla 43","createTime":1681626869267,"updateTime":1681626869267},{"contact":"聯絡方式44","risk":"風險與挑展\r\n blablabla 44","return":"退換貨\r\n blablabla 44","createTime":1681626869268,"updateTime":1681626869268},{"contact":"聯絡方式45","risk":"風險與挑展\r\n blablabla 45","return":"退換貨\r\n blablabla 45","createTime":1681626869269,"updateTime":1681626869269},{"contact":"聯絡方式46","risk":"風險與挑展\r\n blablabla 46","return":"退換貨\r\n blablabla 46","createTime":1681626869270,"updateTime":1681626869270},{"contact":"聯絡方式47","risk":"風險與挑展\r\n blablabla 47","return":"退換貨\r\n blablabla 47","createTime":1681626869271,"updateTime":1681626869271},{"contact":"聯絡方式48","risk":"風險與挑展\r\n blablabla 48","return":"退換貨\r\n blablabla 48","createTime":1681626869272,"updateTime":1681626869272},{"contact":"聯絡方式49","risk":"風險與挑展\r\n blablabla 49","return":"退換貨\r\n blablabla 49","createTime":1681626869273,"updateTime":1681626869273},{"contact":"聯絡方式50","risk":"風險與挑展\r\n blablabla 50","return":"退換貨\r\n blablabla 50","createTime":1681626869274,"updateTime":1681626869274},{"contact":"聯絡方式51","risk":"風險與挑展\r\n blablabla 51","return":"退換貨\r\n blablabla 51","createTime":1681626869275,"updateTime":1681626869275},{"contact":"聯絡方式52","risk":"風險與挑展\r\n blablabla 52","return":"退換貨\r\n blablabla 52","createTime":1681626869276,"updateTime":1681626869276},{"contact":"聯絡方式53","risk":"風險與挑展\r\n blablabla 53","return":"退換貨\r\n blablabla 53","createTime":1681626869277,"updateTime":1681626869277},{"contact":"聯絡方式54","risk":"風險與挑展\r\n blablabla 54","return":"退換貨\r\n blablabla 54","createTime":1681626869278,"updateTime":1681626869278},{"contact":"聯絡方式55","risk":"風險與挑展\r\n blablabla 55","return":"退換貨\r\n blablabla 55","createTime":1681626869279,"updateTime":1681626869279},{"contact":"聯絡方式56","risk":"風險與挑展\r\n blablabla 56","return":"退換貨\r\n blablabla 56","createTime":1681626869280,"updateTime":1681626869280},{"contact":"聯絡方式57","risk":"風險與挑展\r\n blablabla 57","return":"退換貨\r\n blablabla 57","createTime":1681626869281,"updateTime":1681626869281},{"contact":"聯絡方式58","risk":"風險與挑展\r\n blablabla 58","return":"退換貨\r\n blablabla 58","createTime":1681626869282,"updateTime":1681626869282},{"contact":"聯絡方式59","risk":"風險與挑展\r\n blablabla 59","return":"退換貨\r\n blablabla 59","createTime":1681626869283,"updateTime":1681626869283},{"contact":"聯絡方式60","risk":"風險與挑展\r\n blablabla 60","return":"退換貨\r\n blablabla 60","createTime":1681626869284,"updateTime":1681626869284},{"contact":"聯絡方式61","risk":"風險與挑展\r\n blablabla 61","return":"退換貨\r\n blablabla 61","createTime":1681626869285,"updateTime":1681626869285},{"contact":"聯絡方式62","risk":"風險與挑展\r\n blablabla 62","return":"退換貨\r\n blablabla 62","createTime":1681626869286,"updateTime":1681626869286},{"contact":"聯絡方式63","risk":"風險與挑展\r\n blablabla 63","return":"退換貨\r\n blablabla 63","createTime":1681626869287,"updateTime":1681626869287},{"contact":"聯絡方式64","risk":"風險與挑展\r\n blablabla 64","return":"退換貨\r\n blablabla 64","createTime":1681626869288,"updateTime":1681626869288},{"contact":"聯絡方式65","risk":"風險與挑展\r\n blablabla 65","return":"退換貨\r\n blablabla 65","createTime":1681626869289,"updateTime":1681626869289},{"contact":"聯絡方式66","risk":"風險與挑展\r\n blablabla 66","return":"退換貨\r\n blablabla 66","createTime":1681626869290,"updateTime":1681626869290},{"contact":"聯絡方式67","risk":"風險與挑展\r\n blablabla 67","return":"退換貨\r\n blablabla 67","createTime":1681626869291,"updateTime":1681626869291},{"contact":"聯絡方式68","risk":"風險與挑展\r\n blablabla 68","return":"退換貨\r\n blablabla 68","createTime":1681626869292,"updateTime":1681626869292},{"contact":"聯絡方式69","risk":"風險與挑展\r\n blablabla 69","return":"退換貨\r\n blablabla 69","createTime":1681626869293,"updateTime":1681626869293},{"contact":"聯絡方式70","risk":"風險與挑展\r\n blablabla 70","return":"退換貨\r\n blablabla 70","createTime":1681626869294,"updateTime":1681626869294},{"contact":"聯絡方式71","risk":"風險與挑展\r\n blablabla 71","return":"退換貨\r\n blablabla 71","createTime":1681626869295,"updateTime":1681626869295},{"contact":"聯絡方式72","risk":"風險與挑展\r\n blablabla 72","return":"退換貨\r\n blablabla 72","createTime":1681626869296,"updateTime":1681626869296},{"contact":"聯絡方式73","risk":"風險與挑展\r\n blablabla 73","return":"退換貨\r\n blablabla 73","createTime":1681626869297,"updateTime":1681626869297},{"contact":"聯絡方式74","risk":"風險與挑展\r\n blablabla 74","return":"退換貨\r\n blablabla 74","createTime":1681626869298,"updateTime":1681626869298},{"contact":"聯絡方式75","risk":"風險與挑展\r\n blablabla 75","return":"退換貨\r\n blablabla 75","createTime":1681626869299,"updateTime":1681626869299},{"contact":"聯絡方式76","risk":"風險與挑展\r\n blablabla 76","return":"退換貨\r\n blablabla 76","createTime":1681626869300,"updateTime":1681626869300},{"contact":"聯絡方式77","risk":"風險與挑展\r\n blablabla 77","return":"退換貨\r\n blablabla 77","createTime":1681626869301,"updateTime":1681626869301},{"contact":"聯絡方式78","risk":"風險與挑展\r\n blablabla 78","return":"退換貨\r\n blablabla 78","createTime":1681626869302,"updateTime":1681626869302},{"contact":"聯絡方式79","risk":"風險與挑展\r\n blablabla 79","return":"退換貨\r\n blablabla 79","createTime":1681626869303,"updateTime":1681626869303},{"contact":"聯絡方式80","risk":"風險與挑展\r\n blablabla 80","return":"退換貨\r\n blablabla 80","createTime":1681626869304,"updateTime":1681626869304},{"contact":"聯絡方式81","risk":"風險與挑展\r\n blablabla 81","return":"退換貨\r\n blablabla 81","createTime":1681626869305,"updateTime":1681626869305},{"contact":"聯絡方式82","risk":"風險與挑展\r\n blablabla 82","return":"退換貨\r\n blablabla 82","createTime":1681626869306,"updateTime":1681626869306},{"contact":"聯絡方式83","risk":"風險與挑展\r\n blablabla 83","return":"退換貨\r\n blablabla 83","createTime":1681626869307,"updateTime":1681626869307},{"contact":"聯絡方式84","risk":"風險與挑展\r\n blablabla 84","return":"退換貨\r\n blablabla 84","createTime":1681626869308,"updateTime":1681626869308},{"contact":"聯絡方式85","risk":"風險與挑展\r\n blablabla 85","return":"退換貨\r\n blablabla 85","createTime":1681626869309,"updateTime":1681626869309},{"contact":"聯絡方式86","risk":"風險與挑展\r\n blablabla 86","return":"退換貨\r\n blablabla 86","createTime":1681626869310,"updateTime":1681626869310},{"contact":"聯絡方式87","risk":"風險與挑展\r\n blablabla 87","return":"退換貨\r\n blablabla 87","createTime":1681626869311,"updateTime":1681626869311},{"contact":"聯絡方式88","risk":"風險與挑展\r\n blablabla 88","return":"退換貨\r\n blablabla 88","createTime":1681626869312,"updateTime":1681626869312},{"contact":"聯絡方式89","risk":"風險與挑展\r\n blablabla 89","return":"退換貨\r\n blablabla 89","createTime":1681626869313,"updateTime":1681626869313},{"contact":"聯絡方式90","risk":"風險與挑展\r\n blablabla 90","return":"退換貨\r\n blablabla 90","createTime":1681626869314,"updateTime":1681626869314},{"contact":"聯絡方式91","risk":"風險與挑展\r\n blablabla 91","return":"退換貨\r\n blablabla 91","createTime":1681626869315,"updateTime":1681626869315},{"contact":"聯絡方式92","risk":"風險與挑展\r\n blablabla 92","return":"退換貨\r\n blablabla 92","createTime":1681626869316,"updateTime":1681626869316},{"contact":"聯絡方式93","risk":"風險與挑展\r\n blablabla 93","return":"退換貨\r\n blablabla 93","createTime":1681626869317,"updateTime":1681626869317},{"contact":"聯絡方式94","risk":"風險與挑展\r\n blablabla 94","return":"退換貨\r\n blablabla 94","createTime":1681626869318,"updateTime":1681626869318},{"contact":"聯絡方式95","risk":"風險與挑展\r\n blablabla 95","return":"退換貨\r\n blablabla 95","createTime":1681626869319,"updateTime":1681626869319},{"contact":"聯絡方式96","risk":"風險與挑展\r\n blablabla 96","return":"退換貨\r\n blablabla 96","createTime":1681626869320,"updateTime":1681626869320},{"contact":"聯絡方式97","risk":"風險與挑展\r\n blablabla 97","return":"退換貨\r\n blablabla 97","createTime":1681626869321,"updateTime":1681626869321},{"contact":"聯絡方式98","risk":"風險與挑展\r\n blablabla 98","return":"退換貨\r\n blablabla 98","createTime":1681626869322,"updateTime":1681626869322},{"contact":"聯絡方式99","risk":"風險與挑展\r\n blablabla 99","return":"退換貨\r\n blablabla 99","createTime":1681626869323,"updateTime":1681626869323}]